levenshtein.cpython-38-darwin.so
levenshtein.pypy38-pp73-darwin.so
levenshtein/__init__.pyi
levenshtein/py.typed
levenshtein/inc/levenshtein.hpp
levenshtein/src/levenshtein.cpp
levenshtein/src/module.cpp
levenshtein_cpp-0.0.3.dist-info/LICENSE
levenshtein_cpp-0.0.3.dist-info/METADATA
levenshtein_cpp-0.0.3.dist-info/WHEEL
levenshtein_cpp-0.0.3.dist-info/top_level.txt
levenshtein_cpp-0.0.3.dist-info/RECORD
